 {
    "data_dir": "./datasets",
    "labels": "./datasets/TBAQ-cleaned/tbaq_class_timex_labels.txt",
    "model_name_or_path": "roberta-large",
    "output_dir": "./multi_results_2/123",
    "learning_rate": 2e-5,
    "max_seq_length": 128,
    "num_train_epochs": 40,
    "per_gpu_train_batch_size": 8,
    "per_gpu_eval_batch_size": 16,
    "gradient_accumulation_steps": 16,
    "save_steps": 50000,
    "seed": 88,
    "train_matres": false,
    "train_event": true,
    "train_timex": true,
    "train_duration": false,
    "do_train": true,
    "do_eval": false,
    "do_predict": true,
    "overwrite_output_dir": true
}